acornwalk/__init__.py
acornwalk/walk.py
acornwalk-1.0.1.dist-info/METADATA
acornwalk-1.0.1.dist-info/WHEEL
acornwalk-1.0.1.dist-info/licenses/LICENSE
acornwalk-1.0.1.dist-info/RECORD
